txt2dir/__init__.py
txt2dir/cli.py
txt2dir-0.1.4.dist-info/licenses/LICENSE
txt2dir-0.1.4.dist-info/METADATA
txt2dir-0.1.4.dist-info/WHEEL
txt2dir-0.1.4.dist-info/entry_points.txt
txt2dir-0.1.4.dist-info/top_level.txt
txt2dir-0.1.4.dist-info/RECORD
