Metadata-Version: 2.4
Name: txt2dir
Version: 0.1.4
Summary: CLI tool to generate directory structures from text files
Author-email: Sycritz <anis.medjdoul01@gmail.com>
License: MIT
Project-URL: Homepage, https://github.com/Sycritz/txt2dir
Classifier: Programming Language :: Python :: 3
Classifier: Programming Language :: Python :: 3.10
Classifier: Programming Language :: Python :: 3.11
Classifier: Programming Language :: Python :: 3.12
Classifier: License :: OSI Approved :: MIT License
Classifier: Operating System :: OS Independent
Requires-Python: >=3.10
License-File: LICENSE
Requires-Dist: click>=8.0
Dynamic: license-file
